tests/helpers/__init__.py
tests/helpers/foo_service.py
tests/helpers/service_helpers.py
tests/samples/__init__.py
tests/samples/identity_samples.py
tests/samples/load_balancer_samples.py
tests/services/__init__.py
tests/services/test_load_balancer_service.py
tests/services/test_queue_service.py
tests/services/test_service_registry.py
tests/services/test_storage_service.py
tornadorax/__init__.py
tornadorax/errors.py
tornadorax/identity_client.py
tornadorax/utilities.py
tornadorax/services/__init__.py
tornadorax/services/load_balancer_service.py
tornadorax/services/queue_service.py
tornadorax/services/service_registry.py
tornadorax/services/storage_service.py
tornadorax-0.4.0.dist-info/METADATA
tornadorax-0.4.0.dist-info/WHEEL
tornadorax-0.4.0.dist-info/top_level.txt
tornadorax-0.4.0.dist-info/RECORD
