Metadata-Version: 2.1
Name: tornadorax
Version: 0.4.0
Summary: Tornado wrapper for OpenStack services
Home-page: http://github.com/joshmarshall/tornadorax/
Author: Josh Marshall
Author-email: catchjosh@gmail.com
License: http://www.apache.org/licenses/LICENSE-2.0
Platform: UNKNOWN
Requires-Dist: tornado
Requires-Dist: python-dateutil
